[{"name": "US", "num": 7843, "export_tgt": ["CA", "JP", "DE", "GB", "MX", "FR", "AU", "IT", "HK", "CH", "NL", "ES", "BS", "BE", "NZ", "TW", "IL", "CN", "BR", "ZA"], "I": [["I", "Ariocarpus fissuratus", 43, 1, 15653], ["I", "Astrophytum asterias", 42, 1, 38808], ["I", "Ariocarpus retusus", 37, 0, 30309], ["I", "Ariocarpus kotschoubeyanus", 35, 0, 20586], ["I", "Elephas maximus", 33, 1356, 165], ["I", "Mammillaria pectinifera", 33, 0, 7531], ["I", "Paphiopedilum spp.", 33, 1909, 9295]], "II": [["II", "Alligator mississippiensis", 160, 308627, 326886], ["II", "Orchidaceae hybrid", 123, 181030, 616425], ["II", "Macaca fascicularis", 116, 107486, 24107], ["II", "Python reticulatus", 116, 250490, 18243], ["II", "Macaca mulatta", 112, 18893, 225337], ["II", "Ursus americanus", 102, 19213, 871], ["II", "Chlorocebus aethiops", 96, 474, 85424]], "III": [["III", "Odobenus rosmarus", 31, 380, 5151], ["III", "Antilope cervicapra", 22, 4, 16], ["III", "Swietenia macrophylla", 20, 65327, 169464], ["III", "Psittacula krameri", 8, 3506, 11], ["III", "Bothriechis schlegelii", 6, 30, 5], ["III", "Crotalus durissus", 5, 24, 8], ["III", "Arctictis binturong", 4, 0, 1]], "N": [["N", "Trachemys scripta elegans", 8, 2, 0], ["N", "Hippocampus spp.", 4, 0, 0], ["N", "Acrochordus javanicus", 3, 5150, 0], ["N", "Hippocampus erectus", 2, 0, 0], ["N", "Uroplatus lineatus", 2, 0, 0], ["N", "Dendrolagus matschiei", 1, 202, 0], ["N", "Hippocampus ingens", 1, 0, 0]], "Purpose": [["T", 5169], ["P", 694], ["B", 457], ["S", 408], ["Q", 149], ["H", 145], ["Z", 101], ["E", 95], ["M", 73], ["N", 4], ["L", 2], [null, 0]], "coord": [-97.0, 38.0], "nameCN": "\u7f8e\u56fd", "export_tgt_info": [{"name": "\u52a0\u62ff\u5927", "coord": [-95.0, 60.0]}, {"name": "\u65e5\u672c", "coord": [138.0, 36.0]}, {"name": "\u5fb7\u56fd", "coord": [9.0, 51.0]}, {"name": "\u82f1\u56fd", "coord": [-2.0, 54.0]}, {"name": "\u58a8\u897f\u54e5", "coord": [-102.0, 23.0]}, {"name": "\u6cd5\u56fd", "coord": [2.0, 46.0]}, {"name": "\u6fb3\u5927\u5229\u4e9a", "coord": [133.0, -27.0]}, {"name": "\u610f\u5927\u5229", "coord": [12.8333, 42.8333]}, {"name": "\u9999\u6e2f\u7279\u522b\u884c\u653f\u533a", "coord": [114.1667, 22.25]}, {"name": "\u745e\u58eb", "coord": [8.0, 47.0]}, {"name": "\u8377\u5170", "coord": [5.75, 52.5]}, {"name": "\u897f\u73ed\u7259", "coord": [-4.0, 40.0]}, {"name": "\u5df4\u54c8\u9a6c", "coord": [-76.0, 24.25]}, {"name": "\u6bd4\u5229\u65f6", "coord": [4.0, 50.8333]}, {"name": "\u65b0\u897f\u5170", "coord": [174.0, -41.0]}, {"name": "\u53f0\u6e7e\u7701", "coord": [121.0, 23.5]}, {"name": "\u4ee5\u8272\u5217", "coord": [34.75, 31.5]}, {"name": "\u4e2d\u56fd", "coord": [105.0, 35.0]}, {"name": "\u5df4\u897f", "coord": [-55.0, -10.0]}, {"name": "\u5357\u975e", "coord": [24.0, -29.0]}], "purpose_info": [["\u5546\u4e1a", 5169], ["\u4e2a\u4eba", 694], ["\u5708\u517b\u7e41\u6b96\u6216\u4eba\u5de5\u7e41\u6b96", 457], ["\u79d1\u7814", 408], ["\u9a6c\u620f\u548c\u5de1\u56de\u5c55\u89c8", 149], ["\u6218\u5229\u6027\u72e9\u730e", 145], ["\u52a8\u7269\u56ed", 101], ["\u7528\u4e8e\u6559\u80b2", 95], ["\u533b\u836f(\u5305\u62ec\u751f\u7269\u533b\u836f\u7814\u7a76)", 73], ["\u91cd\u65b0\u5f15\u5165\u6216\u5f15\u5165\u91ce\u5916", 4], ["\u6267\u6cd5/\u53f8\u6cd5/\u6cd5\u533b", 2], ["\u672a\u77e5", 0]]}, {"name": "ZA", "num": 4629, "export_tgt": ["US", "DE", "GB", "ES", "JP", "AU", "FR", "NL", "CN", "IT", "CA", "MX", "SG", "PT", "NZ", "SA", "AT", "BE", "ID", "AE"], "I": [["I", "Panthera pardus", 129, 90, 342], ["I", "Acinonyx jubatus", 23, 43, 139], ["I", "Ara macao", 21, 0, 55], ["I", "Encephalartos horridus", 20, 0, 1219], ["I", "Encephalartos lehmannii", 18, 0, 1089], ["I", "Encephalartos trispinosus", 18, 0, 695], ["I", "Encephalartos arenarius", 17, 0, 426]], "II": [["II", "Loxodonta africana", 244, 220, 1153], ["II", "Crocodylus niloticus", 210, 47818, 253090], ["II", "Panthera leo", 183, 115, 542], ["II", "Equus zebra hartmannae", 145, 1026, 499], ["II", "Hippopotamus amphibius", 133, 1259, 2537], ["II", "Ceratotherium simum simum", 84, 0, 403], ["II", "Kobus leche", 80, 25, 312]], "III": [["III", "Damaliscus lunatus", 85, 36, 252], ["III", "Psittacula krameri", 27, 242, 8201], ["III", "Civettictis civetta", 26, 3, 45], ["III", "Tragelaphus spekii", 22, 0, 22], ["III", "Alopochen aegyptiaca", 14, 0, 32], ["III", "Mellivora capensis", 11, 0, 20], ["III", "Plectropterus gambensis", 9, 0, 19]], "N": [["N", "Aloe vera", 2, 0, 1002], ["N", "Brookesia stumpffi", 1, 0, 0], ["N", "Brookesia superciliaris", 1, 0, 0], ["N", "Elaphe taeniura", 1, 0, 0]], "Purpose": [["T", 2364], ["H", 1085], ["P", 649], ["B", 169], ["S", 136], ["Z", 57], ["E", 19], ["G", 11], ["Q", 8], ["M", 1], ["N", 1], [null, 0]], "coord": [24.0, -29.0], "nameCN": "\u5357\u975e", "export_tgt_info": [{"name": "\u7f8e\u56fd", "coord": [-97.0, 38.0]}, {"name": "\u5fb7\u56fd", "coord": [9.0, 51.0]}, {"name": "\u82f1\u56fd", "coord": [-2.0, 54.0]}, {"name": "\u897f\u73ed\u7259", "coord": [-4.0, 40.0]}, {"name": "\u65e5\u672c", "coord": [138.0, 36.0]}, {"name": "\u6fb3\u5927\u5229\u4e9a", "coord": [133.0, -27.0]}, {"name": "\u6cd5\u56fd", "coord": [2.0, 46.0]}, {"name": "\u8377\u5170", "coord": [5.75, 52.5]}, {"name": "\u4e2d\u56fd", "coord": [105.0, 35.0]}, {"name": "\u610f\u5927\u5229", "coord": [12.8333, 42.8333]}, {"name": "\u52a0\u62ff\u5927", "coord": [-95.0, 60.0]}, {"name": "\u58a8\u897f\u54e5", "coord": [-102.0, 23.0]}, {"name": "\u65b0\u52a0\u5761", "coord": [103.8, 1.3667]}, {"name": "\u8461\u8404\u7259", "coord": [-8.0, 39.5]}, {"name": "\u65b0\u897f\u5170", "coord": [174.0, -41.0]}, {"name": "\u6c99\u7279\u963f\u62c9\u4f2f", "coord": [45.0, 25.0]}, {"name": "\u5965\u5730\u5229", "coord": [13.3333, 47.3333]}, {"name": "\u6bd4\u5229\u65f6", "coord": [4.0, 50.8333]}, {"name": "\u5370\u5ea6\u5c3c\u897f\u4e9a", "coord": [120.0, -5.0]}, {"name": "\u963f\u62c9\u4f2f\u8054\u5408\u914b\u957f\u56fd", "coord": [54.0, 24.0]}], "purpose_info": [["\u5546\u4e1a", 2364], ["\u6218\u5229\u6027\u72e9\u730e", 1085], ["\u4e2a\u4eba", 649], ["\u5708\u517b\u7e41\u6b96\u6216\u4eba\u5de5\u7e41\u6b96", 169], ["\u79d1\u7814", 136], ["\u52a8\u7269\u56ed", 57], ["\u7528\u4e8e\u6559\u80b2", 19], ["\u690d\u7269\u56ed", 11], ["\u9a6c\u620f\u548c\u5de1\u56de\u5c55\u89c8", 8], ["\u533b\u836f(\u5305\u62ec\u751f\u7269\u533b\u836f\u7814\u7a76)", 1], ["\u91cd\u65b0\u5f15\u5165\u6216\u5f15\u5165\u91ce\u5916", 1], ["\u672a\u77e5", 0]]}, {"name": "IT", "num": 3705, "export_tgt": ["US", "JP", "CH", "HK", "KR", "RU", "CA", "TW", "CN", "SG", "BR", "SA", "KW", "LB", "TR", "AE", "UA", "IL", "CY", "ZA"], "I": [["I", "Loxodonta africana", 12, 269, 15], ["I", "Elephantidae spp.", 7, 22, 7], ["I", "Falco peregrinus", 7, 8, 4], ["I", "Panthera tigris", 7, 19, 9], ["I", "Elephas maximus", 3, 56, 1], ["I", "Panthera pardus", 3, 43, 3], ["I", "Ailurus fulgens", 1, 0, 1]], "II": [["II", "Python reticulatus", 675, 280483, 271257], ["II", "Ptyas mucosus", 418, 15219, 87910], ["II", "Alligator mississippiensis", 354, 123147, 163451], ["II", "Varanus salvator", 232, 191561, 52708], ["II", "Varanus niloticus", 222, 164193, 151278], ["II", "Tupinambis teguixin", 186, 76365, 62329], ["II", "Caiman crocodilus crocodilus", 154, 19905, 52375]], "III": [["III", "Mustela sibirica", 43, 8161, 833], ["III", "Mustela altaica", 24, 801, 375], ["III", "Cerberus rynchops", 7, 0, 748], ["III", "Daboia russelii", 3, 0, 81], ["III", "Hystrix cristata", 1, 0, 0], ["III", "Micrurus nigrocinctus", 1, 0, 0]], "N": [["N", "Acrochordus javanicus", 33, 0, 6800], ["N", "Enhydris bocourti", 1, 0, 8], ["N", "Hippocampus erectus", 1, 0, 0], ["N", "Homalopsis buccata", 1, 0, 3]], "Purpose": [["T", 3021], ["P", 587], ["Q", 25], ["E", 11], ["H", 4], ["Z", 4], ["B", 1], ["S", 1], [null, 0]], "coord": [12.8333, 42.8333], "nameCN": "\u610f\u5927\u5229", "export_tgt_info": [{"name": "\u7f8e\u56fd", "coord": [-97.0, 38.0]}, {"name": "\u65e5\u672c", "coord": [138.0, 36.0]}, {"name": "\u745e\u58eb", "coord": [8.0, 47.0]}, {"name": "\u9999\u6e2f\u7279\u522b\u884c\u653f\u533a", "coord": [114.1667, 22.25]}, {"name": "\u97e9\u56fd", "coord": [127.5, 37.0]}, {"name": "\u4fc4\u7f57\u65af", "coord": [100.0, 60.0]}, {"name": "\u52a0\u62ff\u5927", "coord": [-95.0, 60.0]}, {"name": "\u53f0\u6e7e\u7701", "coord": [121.0, 23.5]}, {"name": "\u4e2d\u56fd", "coord": [105.0, 35.0]}, {"name": "\u65b0\u52a0\u5761", "coord": [103.8, 1.3667]}, {"name": "\u5df4\u897f", "coord": [-55.0, -10.0]}, {"name": "\u6c99\u7279\u963f\u62c9\u4f2f", "coord": [45.0, 25.0]}, {"name": "\u79d1\u5a01\u7279", "coord": [47.6581, 29.3375]}, {"name": "\u9ece\u5df4\u5ae9", "coord": [35.8333, 33.8333]}, {"name": "\u571f\u8033\u5176", "coord": [35.0, 39.0]}, {"name": "\u963f\u62c9\u4f2f\u8054\u5408\u914b\u957f\u56fd", "coord": [54.0, 24.0]}, {"name": "\u4e4c\u514b\u5170", "coord": [32.0, 49.0]}, {"name": "\u4ee5\u8272\u5217", "coord": [34.75, 31.5]}, {"name": "\u585e\u6d66\u8def\u65af", "coord": [33.0, 35.0]}, {"name": "\u5357\u975e", "coord": [24.0, -29.0]}], "purpose_info": [["\u5546\u4e1a", 3021], ["\u4e2a\u4eba", 587], ["\u9a6c\u620f\u548c\u5de1\u56de\u5c55\u89c8", 25], ["\u7528\u4e8e\u6559\u80b2", 11], ["\u6218\u5229\u6027\u72e9\u730e", 4], ["\u52a8\u7269\u56ed", 4], ["\u5708\u517b\u7e41\u6b96\u6216\u4eba\u5de5\u7e41\u6b96", 1], ["\u79d1\u7814", 1], ["\u672a\u77e5", 0]]}, {"name": "CH", "num": 3607, "export_tgt": ["US", "DE", "FR", "IT", "GB", "AT", "JP", "BE", "MX", "HK", "NL", "ZA", "DK", "PT", "SG", "ES", "GR", "CA", "KR", "TH"], "I": [["I", "Elephantidae spp.", 44, 269, 300], ["I", "Callimico goeldii", 10, 4, 13], ["I", "Cheloniidae spp.", 10, 15, 17], ["I", "Panthera pardus", 10, 16, 7], ["I", "Ara ambiguus", 8, 14, 10], ["I", "Crocodylus moreletii", 7, 110, 396], ["I", "Pachypodium baronii", 7, 9, 624]], "II": [["II", "Alligator mississippiensis", 412, 568547, 454216], ["II", "Varanus niloticus", 331, 85402, 72793], ["II", "Caiman crocodilus fuscus", 293, 199159, 152957], ["II", "Python reticulatus", 216, 29258, 18891], ["II", "Varanus salvator", 184, 23999, 31991], ["II", "Caiman crocodilus crocodilus", 167, 3519, 12752], ["II", "Crocodylus niloticus", 158, 20162, 5970]], "III": [["III", "Bothriechis schlegelii", 4, 0, 10], ["III", "Potos flavus", 2, 0, 2], ["III", "Daboia russelii", 1, 1, 10], ["III", "Damaliscus lunatus", 1, 2, 0], ["III", "Gazella dorcas", 1, 2, 0], ["III", "Mustela sibirica", 1, 428, 0], ["III", "Psittacula krameri", 1, 10, 0]], "N": [["N", "Acrochordus javanicus", 3, 1, 0]], "Purpose": [["T", 945], ["P", 56], ["B", 41], ["Z", 34], ["Q", 18], ["S", 15], ["H", 14], ["E", 13], ["G", 7], ["M", 5], ["N", 5], [null, 0]], "coord": [8.0, 47.0], "nameCN": "\u745e\u58eb", "export_tgt_info": [{"name": "\u7f8e\u56fd", "coord": [-97.0, 38.0]}, {"name": "\u5fb7\u56fd", "coord": [9.0, 51.0]}, {"name": "\u6cd5\u56fd", "coord": [2.0, 46.0]}, {"name": "\u610f\u5927\u5229", "coord": [12.8333, 42.8333]}, {"name": "\u82f1\u56fd", "coord": [-2.0, 54.0]}, {"name": "\u5965\u5730\u5229", "coord": [13.3333, 47.3333]}, {"name": "\u65e5\u672c", "coord": [138.0, 36.0]}, {"name": "\u6bd4\u5229\u65f6", "coord": [4.0, 50.8333]}, {"name": "\u58a8\u897f\u54e5", "coord": [-102.0, 23.0]}, {"name": "\u9999\u6e2f\u7279\u522b\u884c\u653f\u533a", "coord": [114.1667, 22.25]}, {"name": "\u8377\u5170", "coord": [5.75, 52.5]}, {"name": "\u5357\u975e", "coord": [24.0, -29.0]}, {"name": "\u4e39\u9ea6", "coord": [10.0, 56.0]}, {"name": "\u8461\u8404\u7259", "coord": [-8.0, 39.5]}, {"name": "\u65b0\u52a0\u5761", "coord": [103.8, 1.3667]}, {"name": "\u897f\u73ed\u7259", "coord": [-4.0, 40.0]}, {"name": "\u5e0c\u814a", "coord": [22.0, 39.0]}, {"name": "\u52a0\u62ff\u5927", "coord": [-95.0, 60.0]}, {"name": "\u97e9\u56fd", "coord": [127.5, 37.0]}, {"name": "\u6cf0\u56fd", "coord": [100.0, 15.0]}], "purpose_info": [["\u5546\u4e1a", 945], ["\u4e2a\u4eba", 56], ["\u5708\u517b\u7e41\u6b96\u6216\u4eba\u5de5\u7e41\u6b96", 41], ["\u52a8\u7269\u56ed", 34], ["\u9a6c\u620f\u548c\u5de1\u56de\u5c55\u89c8", 18], ["\u79d1\u7814", 15], ["\u6218\u5229\u6027\u72e9\u730e", 14], ["\u7528\u4e8e\u6559\u80b2", 13], ["\u690d\u7269\u56ed", 7], ["\u533b\u836f(\u5305\u62ec\u751f\u7269\u533b\u836f\u7814\u7a76)", 5], ["\u91cd\u65b0\u5f15\u5165\u6216\u5f15\u5165\u91ce\u5916", 5], ["\u672a\u77e5", 0]]}, {"name": "ID", "num": 3559, "export_tgt": ["US", "JP", "DE", "GB", "ES", "CZ", "FR", "IT", "CA", "CH", "NL", "AU", "TW", "KR", "DK", "BE", "HK", "IL", "BR", "ZA"], "I": [["I", "Scleropages formosus", 8, 35, 22885], ["I", "Pongo pygmaeus", 4, 4, 635], ["I", "Chelonia mydas", 3, 0, 106], ["I", "Cheloniidae spp.", 3, 0, 0], ["I", "Panthera tigris", 3, 0, 4], ["I", "Ara macao", 2, 14, 2], ["I", "Dicerorhinus sumatrensis", 2, 0, 700]], "II": [["II", "Scleractinia spp.", 60, 393, 787399], ["II", "Python reticulatus", 57, 351, 167855], ["II", "Heliofungia actiniformis", 45, 0, 53274], ["II", "Trachyphyllia geoffroyi", 39, 0, 80491], ["II", "Goniopora minor", 37, 0, 43140], ["II", "Turbinaria mesenterina", 35, 0, 16462], ["II", "Caulastraea tumida", 34, 0, 12558]], "III": [["III", "Cerberus rynchops", 15, 0, 41526], ["III", "Odobenus rosmarus", 10, 5048, 213], ["III", "Daboia russelii", 3, 0, 4], ["III", "Euplectes macroura", 1, 0, 0], ["III", "Paguma larvata", 1, 0, 0], ["III", "Paradoxurus hermaphroditus", 1, 0, 0], ["III", "Xenochrophis piscator", 1, 0, 0]], "N": [["N", "Elaphe radiata", 6, 0, 0], ["N", "Hippocampus kuda", 6, 0, 0], ["N", "Hippocampus spp.", 6, 0, 0], ["N", "Homalopsis buccata", 6, 0, 0], ["N", "Hippocampus erectus", 5, 0, 0], ["N", "Boiga dendrophila", 4, 0, 0], ["N", "Tiliqua scincoides", 4, 0, 0], ["N", "Acrochordus javanicus", 3, 0, 0]], "Purpose": [["T", 3311], ["P", 63], ["G", 43], ["S", 30], ["B", 10], ["Z", 10], ["Q", 3], ["E", 1], ["M", 1], [null, 0]], "coord": [120.0, -5.0], "nameCN": "\u5370\u5ea6\u5c3c\u897f\u4e9a", "export_tgt_info": [{"name": "\u7f8e\u56fd", "coord": [-97.0, 38.0]}, {"name": "\u65e5\u672c", "coord": [138.0, 36.0]}, {"name": "\u5fb7\u56fd", "coord": [9.0, 51.0]}, {"name": "\u82f1\u56fd", "coord": [-2.0, 54.0]}, {"name": "\u897f\u73ed\u7259", "coord": [-4.0, 40.0]}, {"name": "\u6377\u514b", "coord": [15.5, 49.75]}, {"name": "\u6cd5\u56fd", "coord": [2.0, 46.0]}, {"name": "\u610f\u5927\u5229", "coord": [12.8333, 42.8333]}, {"name": "\u52a0\u62ff\u5927", "coord": [-95.0, 60.0]}, {"name": "\u745e\u58eb", "coord": [8.0, 47.0]}, {"name": "\u8377\u5170", "coord": [5.75, 52.5]}, {"name": "\u6fb3\u5927\u5229\u4e9a", "coord": [133.0, -27.0]}, {"name": "\u53f0\u6e7e\u7701", "coord": [121.0, 23.5]}, {"name": "\u97e9\u56fd", "coord": [127.5, 37.0]}, {"name": "\u4e39\u9ea6", "coord": [10.0, 56.0]}, {"name": "\u6bd4\u5229\u65f6", "coord": [4.0, 50.8333]}, {"name": "\u9999\u6e2f\u7279\u522b\u884c\u653f\u533a", "coord": [114.1667, 22.25]}, {"name": "\u4ee5\u8272\u5217", "coord": [34.75, 31.5]}, {"name": "\u5df4\u897f", "coord": [-55.0, -10.0]}, {"name": "\u5357\u975e", "coord": [24.0, -29.0]}], "purpose_info": [["\u5546\u4e1a", 3311], ["\u4e2a\u4eba", 63], ["\u690d\u7269\u56ed", 43], ["\u79d1\u7814", 30], ["\u5708\u517b\u7e41\u6b96\u6216\u4eba\u5de5\u7e41\u6b96", 10], ["\u52a8\u7269\u56ed", 10], ["\u9a6c\u620f\u548c\u5de1\u56de\u5c55\u89c8", 3], ["\u7528\u4e8e\u6559\u80b2", 1], ["\u533b\u836f(\u5305\u62ec\u751f\u7269\u533b\u836f\u7814\u7a76)", 1], ["\u672a\u77e5", 0]]}, {"name": "CA", "num": 2857, "export_tgt": ["US", "DE", "JP", "FR", "GB", "CH", "IT", "AU", "NO", "SE", "AT", "ES", "BE", "DK", "MX", "NL", "HK", "CN", "PL", "NZ"], "I": [["I", "Falco rusticolus", 21, 1, 45], ["I", "Elephas maximus", 19, 126, 432], ["I", "Falco peregrinus", 14, 4, 21], ["I", "Falco hybrid", 8, 2, 18], ["I", "Mustela nigripes", 7, 14, 333], ["I", "Panthera tigris", 6, 54, 7], ["I", "Acinonyx jubatus", 5, 2, 4]], "II": [["II", "Ursus americanus", 371, 285, 24549], ["II", "Canis lupus", 173, 1272, 6573], ["II", "Lynx canadensis", 142, 1948, 11896], ["II", "Ursus arctos", 121, 329, 1128], ["II", "Ursus maritimus", 93, 174, 479], ["II", "Puma concolor", 90, 12, 1087], ["II", "Lynx rufus", 71, 10652, 10412]], "III": [["III", "Odobenus rosmarus", 35, 147, 162], ["III", "Panax quinquefolius", 29, 15080, 4230460], ["III", "Swietenia macrophylla", 11, 149095, 26304], ["III", "Anas acuta", 8, 0, 9], ["III", "Anas crecca", 5, 0, 14], ["III", "Mustela sibirica", 5, 195, 8], ["III", "Damaliscus lunatus", 4, 11, 0]], "N": [["N", "Dendrolagus matschiei", 1, 0, 0]], "Purpose": [["T", 1215], ["P", 775], ["H", 313], ["S", 176], ["B", 46], ["E", 44], ["Z", 44], ["Q", 25], ["L", 12], ["M", 3], ["N", 2], [null, 0]], "coord": [-95.0, 60.0], "nameCN": "\u52a0\u62ff\u5927", "export_tgt_info": [{"name": "\u7f8e\u56fd", "coord": [-97.0, 38.0]}, {"name": "\u5fb7\u56fd", "coord": [9.0, 51.0]}, {"name": "\u65e5\u672c", "coord": [138.0, 36.0]}, {"name": "\u6cd5\u56fd", "coord": [2.0, 46.0]}, {"name": "\u82f1\u56fd", "coord": [-2.0, 54.0]}, {"name": "\u745e\u58eb", "coord": [8.0, 47.0]}, {"name": "\u610f\u5927\u5229", "coord": [12.8333, 42.8333]}, {"name": "\u6fb3\u5927\u5229\u4e9a", "coord": [133.0, -27.0]}, {"name": "\u632a\u5a01", "coord": [10.0, 62.0]}, {"name": "\u745e\u5178", "coord": [15.0, 62.0]}, {"name": "\u5965\u5730\u5229", "coord": [13.3333, 47.3333]}, {"name": "\u897f\u73ed\u7259", "coord": [-4.0, 40.0]}, {"name": "\u6bd4\u5229\u65f6", "coord": [4.0, 50.8333]}, {"name": "\u4e39\u9ea6", "coord": [10.0, 56.0]}, {"name": "\u58a8\u897f\u54e5", "coord": [-102.0, 23.0]}, {"name": "\u8377\u5170", "coord": [5.75, 52.5]}, {"name": "\u9999\u6e2f\u7279\u522b\u884c\u653f\u533a", "coord": [114.1667, 22.25]}, {"name": "\u4e2d\u56fd", "coord": [105.0, 35.0]}, {"name": "\u6ce2\u5170", "coord": [20.0, 52.0]}, {"name": "\u65b0\u897f\u5170", "coord": [174.0, -41.0]}], "purpose_info": [["\u5546\u4e1a", 1215], ["\u4e2a\u4eba", 775], ["\u6218\u5229\u6027\u72e9\u730e", 313], ["\u79d1\u7814", 176], ["\u5708\u517b\u7e41\u6b96\u6216\u4eba\u5de5\u7e41\u6b96", 46], ["\u7528\u4e8e\u6559\u80b2", 44], ["\u52a8\u7269\u56ed", 44], ["\u9a6c\u620f\u548c\u5de1\u56de\u5c55\u89c8", 25], ["\u6267\u6cd5/\u53f8\u6cd5/\u6cd5\u533b", 12], ["\u533b\u836f(\u5305\u62ec\u751f\u7269\u533b\u836f\u7814\u7a76)", 3], ["\u91cd\u65b0\u5f15\u5165\u6216\u5f15\u5165\u91ce\u5916", 2], ["\u672a\u77e5", 0]]}, {"name": "FR", "num": 2533, "export_tgt": ["US", "CH", "JP", "HK", "CA", "KR", "CN", "SG", "PL", "TW", "SA", "RU", "BR", "AU", "AE", "MU", "TH", "MX", "TR", "MC"], "I": [["I", "Elephantidae spp.", 34, 58, 331], ["I", "Eretmochelys imbricata", 8, 8, 2], ["I", "Panthera pardus", 8, 182, 16], ["I", "Elephas maximus", 7, 1, 11], ["I", "Cheloniidae spp.", 5, 11, 9], ["I", "Pantholops hodgsonii", 5, 0, 4], ["I", "Paphiopedilum spp.", 5, 3, 39]], "II": [["II", "Alligator mississippiensis", 313, 186379, 651990], ["II", "Python reticulatus", 302, 50502, 26675], ["II", "Varanus niloticus", 257, 47922, 292897], ["II", "Crocodylus porosus", 192, 10630, 4861], ["II", "Crocodylus niloticus", 148, 28094, 14972], ["II", "Caiman crocodilus fuscus", 91, 64718, 262031], ["II", "Ptyas mucosus", 85, 350, 7465]], "III": [["III", "Civettictis civetta", 7, 9, 41], ["III", "Cairina moschata", 6, 0, 266854], ["III", "Daboia russelii", 6, 0, 37], ["III", "Odobenus rosmarus", 3, 17, 1], ["III", "Antilope cervicapra", 2, 3, 1], ["III", "Estrilda melpoda", 2, 1100, 400], ["III", "Mustela erminea ferghanae", 2, 0, 1]], "N": [], "Purpose": [["T", 1556], ["P", 591], ["B", 57], ["Z", 48], ["Q", 38], ["H", 37], ["L", 20], ["S", 19], ["E", 6], ["N", 3], ["M", 1], [null, 0]], "coord": [2.0, 46.0], "nameCN": "\u6cd5\u56fd", "export_tgt_info": [{"name": "\u7f8e\u56fd", "coord": [-97.0, 38.0]}, {"name": "\u745e\u58eb", "coord": [8.0, 47.0]}, {"name": "\u65e5\u672c", "coord": [138.0, 36.0]}, {"name": "\u9999\u6e2f\u7279\u522b\u884c\u653f\u533a", "coord": [114.1667, 22.25]}, {"name": "\u52a0\u62ff\u5927", "coord": [-95.0, 60.0]}, {"name": "\u97e9\u56fd", "coord": [127.5, 37.0]}, {"name": "\u4e2d\u56fd", "coord": [105.0, 35.0]}, {"name": "\u65b0\u52a0\u5761", "coord": [103.8, 1.3667]}, {"name": "\u6ce2\u5170", "coord": [20.0, 52.0]}, {"name": "\u53f0\u6e7e\u7701", "coord": [121.0, 23.5]}, {"name": "\u6c99\u7279\u963f\u62c9\u4f2f", "coord": [45.0, 25.0]}, {"name": "\u4fc4\u7f57\u65af", "coord": [100.0, 60.0]}, {"name": "\u5df4\u897f", "coord": [-55.0, -10.0]}, {"name": "\u6fb3\u5927\u5229\u4e9a", "coord": [133.0, -27.0]}, {"name": "\u963f\u62c9\u4f2f\u8054\u5408\u914b\u957f\u56fd", "coord": [54.0, 24.0]}, {"name": "\u6bdb\u91cc\u6c42\u65af", "coord": [57.55, -20.2833]}, {"name": "\u6cf0\u56fd", "coord": [100.0, 15.0]}, {"name": "\u58a8\u897f\u54e5", "coord": [-102.0, 23.0]}, {"name": "\u571f\u8033\u5176", "coord": [35.0, 39.0]}, {"name": "\u6469\u7eb3\u54e5", "coord": [7.4, 43.7333]}], "purpose_info": [["\u5546\u4e1a", 1556], ["\u4e2a\u4eba", 591], ["\u5708\u517b\u7e41\u6b96\u6216\u4eba\u5de5\u7e41\u6b96", 57], ["\u52a8\u7269\u56ed", 48], ["\u9a6c\u620f\u548c\u5de1\u56de\u5c55\u89c8", 38], ["\u6218\u5229\u6027\u72e9\u730e", 37], ["\u6267\u6cd5/\u53f8\u6cd5/\u6cd5\u533b", 20], ["\u79d1\u7814", 19], ["\u7528\u4e8e\u6559\u80b2", 6], ["\u91cd\u65b0\u5f15\u5165\u6216\u5f15\u5165\u91ce\u5916", 3], ["\u533b\u836f(\u5305\u62ec\u751f\u7269\u533b\u836f\u7814\u7a76)", 1], ["\u672a\u77e5", 0]]}, {"name": "DE", "num": 2162, "export_tgt": ["CH", "US", "JP", "CZ", "MC", "HK", "ZA", "CA", "TH", "PL", "HU", "KR", "RU", "TR", "SG", "AE", "TW", "CL", "IL", "MX"], "I": [["I", "Falco peregrinus", 17, 16, 25], ["I", "Falco hybrid", 15, 32, 668], ["I", "Elephas maximus", 13, 302, 44], ["I", "Falco rusticolus", 13, 17, 59], ["I", "Ariocarpus fissuratus", 11, 812, 52], ["I", "Ariocarpus retusus", 11, 860, 108], ["I", "Ariocarpus kotschoubeyanus", 10, 500, 63]], "II": [["II", "Alligator mississippiensis", 79, 37633, 31918], ["II", "Crocodylus niloticus", 58, 15264, 7430], ["II", "Acipenser stellatus", 57, 10659, 4686], ["II", "Loxodonta africana", 42, 561, 251], ["II", "Python reticulatus", 39, 88511, 2021], ["II", "Varanus salvator", 39, 41926, 10355], ["II", "Caiman crocodilus fuscus", 36, 68625, 40268]], "III": [["III", "Mustela sibirica", 59, 8887, 150300], ["III", "Psittacula krameri", 4, 307, 8], ["III", "Amandava subflava", 3, 1775, 220], ["III", "Lagonosticta senegala", 3, 1500, 195], ["III", "Odobenus rosmarus", 3, 106, 4], ["III", "Serinus mozambicus", 3, 4900, 1025], ["III", "Amadina fasciata", 2, 4375, 372]], "N": [["N", "Trachemys scripta elegans", 2, 0, 9], ["N", "Aloe vera", 1, 0, 0], ["N", "Lophura leucomelanos", 1, 0, 4]], "Purpose": [["T", 1422], ["P", 158], ["Z", 132], ["G", 40], ["Q", 38], ["S", 38], ["B", 22], ["M", 17], ["E", 8], ["N", 6], ["H", 2], [null, 0]], "coord": [9.0, 51.0], "nameCN": "\u5fb7\u56fd", "export_tgt_info": [{"name": "\u745e\u58eb", "coord": [8.0, 47.0]}, {"name": "\u7f8e\u56fd", "coord": [-97.0, 38.0]}, {"name": "\u65e5\u672c", "coord": [138.0, 36.0]}, {"name": "\u6377\u514b", "coord": [15.5, 49.75]}, {"name": "\u6469\u7eb3\u54e5", "coord": [7.4, 43.7333]}, {"name": "\u9999\u6e2f\u7279\u522b\u884c\u653f\u533a", "coord": [114.1667, 22.25]}, {"name": "\u5357\u975e", "coord": [24.0, -29.0]}, {"name": "\u52a0\u62ff\u5927", "coord": [-95.0, 60.0]}, {"name": "\u6cf0\u56fd", "coord": [100.0, 15.0]}, {"name": "\u6ce2\u5170", "coord": [20.0, 52.0]}, {"name": "\u5308\u7259\u5229", "coord": [20.0, 47.0]}, {"name": "\u97e9\u56fd", "coord": [127.5, 37.0]}, {"name": "\u4fc4\u7f57\u65af", "coord": [100.0, 60.0]}, {"name": "\u571f\u8033\u5176", "coord": [35.0, 39.0]}, {"name": "\u65b0\u52a0\u5761", "coord": [103.8, 1.3667]}, {"name": "\u963f\u62c9\u4f2f\u8054\u5408\u914b\u957f\u56fd", "coord": [54.0, 24.0]}, {"name": "\u53f0\u6e7e\u7701", "coord": [121.0, 23.5]}, {"name": "\u667a\u5229", "coord": [-71.0, -30.0]}, {"name": "\u4ee5\u8272\u5217", "coord": [34.75, 31.5]}, {"name": "\u58a8\u897f\u54e5", "coord": [-102.0, 23.0]}], "purpose_info": [["\u5546\u4e1a", 1422], ["\u4e2a\u4eba", 158], ["\u52a8\u7269\u56ed", 132], ["\u690d\u7269\u56ed", 40], ["\u9a6c\u620f\u548c\u5de1\u56de\u5c55\u89c8", 38], ["\u79d1\u7814", 38], ["\u5708\u517b\u7e41\u6b96\u6216\u4eba\u5de5\u7e41\u6b96", 22], ["\u533b\u836f(\u5305\u62ec\u751f\u7269\u533b\u836f\u7814\u7a76)", 17], ["\u7528\u4e8e\u6559\u80b2", 8], ["\u91cd\u65b0\u5f15\u5165\u6216\u5f15\u5165\u91ce\u5916", 6], ["\u6218\u5229\u6027\u72e9\u730e", 2], ["\u672a\u77e5", 0]]}, {"name": "AU", "num": 1997, "export_tgt": ["US", "JP", "TH", "GB", "CA", "TW", "DE", "NZ", "BR", "ES", "IT", "SG", "XX", "HK", "BS", "ID", "PK", "RU", "FR", "ZA"], "I": [["I", "Loxodonta africana", 11, 103, 36], ["I", "Ceratozamia hildae", 10, 0, 43], ["I", "Elephantidae spp.", 10, 152, 61], ["I", "Encephalartos arenarius", 8, 7, 30], ["I", "Ceratozamia mexicana", 7, 0, 37], ["I", "Elephas maximus", 7, 1, 34], ["I", "Stangeria eriopus", 7, 0, 16]], "II": [["II", "Crocodylus porosus", 190, 63791, 80371], ["II", "Ornithoptera priamus", 31, 437, 738], ["II", "Crocodylia spp.", 25, 0, 0], ["II", "Dicksonia antarctica", 20, 0, 93487], ["II", "Macrozamia moorei", 19, 0, 1578], ["II", "Dendrobium spp.", 17, 17, 3975], ["II", "Nepenthes spp.", 14, 0, 400]], "III": [["III", "Bubalus arnee", 3, 0, 0], ["III", "Uraeginthus bengalus", 2, 15, 0], ["III", "Antilope cervicapra", 1, 0, 0], ["III", "Bubulcus ibis", 1, 0, 0], ["III", "Odobenus rosmarus", 1, 2, 0], ["III", "Ploceus cucullatus", 1, 20, 0]], "N": [["N", "Hippocampus abdominalis", 3, 0, 0], ["N", "Hippocampus kuda", 1, 0, 0]], "Purpose": [["T", 1386], ["P", 165], ["S", 52], ["Q", 22], ["Z", 19], ["B", 6], ["H", 5], ["E", 1], [null, 0]], "coord": [133.0, -27.0], "nameCN": "\u6fb3\u5927\u5229\u4e9a", "export_tgt_info": [{"name": "\u7f8e\u56fd", "coord": [-97.0, 38.0]}, {"name": "\u65e5\u672c", "coord": [138.0, 36.0]}, {"name": "\u6cf0\u56fd", "coord": [100.0, 15.0]}, {"name": "\u82f1\u56fd", "coord": [-2.0, 54.0]}, {"name": "\u52a0\u62ff\u5927", "coord": [-95.0, 60.0]}, {"name": "\u53f0\u6e7e\u7701", "coord": [121.0, 23.5]}, {"name": "\u5fb7\u56fd", "coord": [9.0, 51.0]}, {"name": "\u65b0\u897f\u5170", "coord": [174.0, -41.0]}, {"name": "\u5df4\u897f", "coord": [-55.0, -10.0]}, {"name": "\u897f\u73ed\u7259", "coord": [-4.0, 40.0]}, {"name": "\u610f\u5927\u5229", "coord": [12.8333, 42.8333]}, {"name": "\u65b0\u52a0\u5761", "coord": [103.8, 1.3667]}, {"name": "\u672a\u77e5", "coord": [0, 0]}, {"name": "\u9999\u6e2f\u7279\u522b\u884c\u653f\u533a", "coord": [114.1667, 22.25]}, {"name": "\u5df4\u54c8\u9a6c", "coord": [-76.0, 24.25]}, {"name": "\u5370\u5ea6\u5c3c\u897f\u4e9a", "coord": [120.0, -5.0]}, {"name": "\u5df4\u57fa\u65af\u5766", "coord": [70.0, 30.0]}, {"name": "\u4fc4\u7f57\u65af", "coord": [100.0, 60.0]}, {"name": "\u6cd5\u56fd", "coord": [2.0, 46.0]}, {"name": "\u5357\u975e", "coord": [24.0, -29.0]}], "purpose_info": [["\u5546\u4e1a", 1386], ["\u4e2a\u4eba", 165], ["\u79d1\u7814", 52], ["\u9a6c\u620f\u548c\u5de1\u56de\u5c55\u89c8", 22], ["\u52a8\u7269\u56ed", 19], ["\u5708\u517b\u7e41\u6b96\u6216\u4eba\u5de5\u7e41\u6b96", 6], ["\u6218\u5229\u6027\u72e9\u730e", 5], ["\u7528\u4e8e\u6559\u80b2", 1], ["\u672a\u77e5", 0]]}, {"name": "NL", "num": 1952, "export_tgt": ["MT", "US", "JP", "CA", "TW", "CH", "IL", "CN", "NO", "LK", "SG", "AN", "PH", "CY", "MX", "ZA", "ID", "DO", "MY", "PK"], "I": [["I", "Elephantidae spp.", 17, 45, 72], ["I", "Loxodonta africana", 7, 150, 49], ["I", "Lophophorus impejanus", 6, 0, 46], ["I", "Psephotus dissimilis", 6, 0, 38], ["I", "Pyrrhura cruentata", 6, 0, 12], ["I", "Syrmaticus ellioti", 6, 0, 52], ["I", "Cheloniidae spp.", 5, 4, 32]], "II": [["II", "Psittacus erithacus", 56, 13595, 1692], ["II", "Platycercus eximius", 41, 0, 4963], ["II", "Platycercus elegans", 33, 0, 1949], ["II", "Ara ararauna", 32, 603, 270], ["II", "Agapornis personatus", 31, 0, 4020], ["II", "Agapornis roseicollis", 31, 11, 4002], ["II", "Psephotus haematonotus", 29, 0, 3972]], "III": [["III", "Psittacula krameri", 39, 337, 2423], ["III", "Serinus mozambicus", 13, 11210, 7972], ["III", "Serinus leucopygius", 7, 4650, 4023], ["III", "Amadina fasciata", 6, 3100, 1419], ["III", "Anas clypeata", 6, 0, 32], ["III", "Anas penelope", 6, 0, 26], ["III", "Lophura ignita", 6, 0, 60]], "N": [["N", "Lophura diardi", 4, 0, 14], ["N", "Lophura inornata", 1, 0, 2], ["N", "Lophura leucomelanos", 1, 0, 9]], "Purpose": [["T", 1622], ["Z", 84], ["P", 64], ["B", 48], ["N", 21], ["E", 18], ["L", 17], ["Q", 11], ["S", 9], ["G", 1], [null, 0]], "coord": [5.75, 52.5], "nameCN": "\u8377\u5170", "export_tgt_info": [{"name": "\u9a6c\u8033\u4ed6", "coord": [14.5833, 35.8333]}, {"name": "\u7f8e\u56fd", "coord": [-97.0, 38.0]}, {"name": "\u65e5\u672c", "coord": [138.0, 36.0]}, {"name": "\u52a0\u62ff\u5927", "coord": [-95.0, 60.0]}, {"name": "\u53f0\u6e7e\u7701", "coord": [121.0, 23.5]}, {"name": "\u745e\u58eb", "coord": [8.0, 47.0]}, {"name": "\u4ee5\u8272\u5217", "coord": [34.75, 31.5]}, {"name": "\u4e2d\u56fd", "coord": [105.0, 35.0]}, {"name": "\u632a\u5a01", "coord": [10.0, 62.0]}, {"name": "\u65af\u91cc\u5170\u5361", "coord": [81.0, 7.0]}, {"name": "\u65b0\u52a0\u5761", "coord": [103.8, 1.3667]}, {"name": "\u672a\u77e5", "coord": [0, 0]}, {"name": "\u83f2\u5f8b\u5bbe", "coord": [122.0, 13.0]}, {"name": "\u585e\u6d66\u8def\u65af", "coord": [33.0, 35.0]}, {"name": "\u58a8\u897f\u54e5", "coord": [-102.0, 23.0]}, {"name": "\u5357\u975e", "coord": [24.0, -29.0]}, {"name": "\u5370\u5ea6\u5c3c\u897f\u4e9a", "coord": [120.0, -5.0]}, {"name": "\u591a\u7c73\u5c3c\u52a0\u5171\u548c\u56fd", "coord": [-70.6667, 19.0]}, {"name": "\u9a6c\u6765\u897f\u4e9a", "coord": [112.5, 2.5]}, {"name": "\u5df4\u57fa\u65af\u5766", "coord": [70.0, 30.0]}], "purpose_info": [["\u5546\u4e1a", 1622], ["\u52a8\u7269\u56ed", 84], ["\u4e2a\u4eba", 64], ["\u5708\u517b\u7e41\u6b96\u6216\u4eba\u5de5\u7e41\u6b96", 48], ["\u91cd\u65b0\u5f15\u5165\u6216\u5f15\u5165\u91ce\u5916", 21], ["\u7528\u4e8e\u6559\u80b2", 18], ["\u6267\u6cd5/\u53f8\u6cd5/\u6cd5\u533b", 17], ["\u9a6c\u620f\u548c\u5de1\u56de\u5c55\u89c8", 11], ["\u79d1\u7814", 9], ["\u690d\u7269\u56ed", 1], ["\u672a\u77e5", 0]]}, {"name": "BR", "num": 1827, "export_tgt": ["US", "DE", "JP", "GB", "CH", "HK", "CA", "FR", "AT", "PT", "IT", "VE", "CL", "AU", "ES", "TW", "UY", "EC", "AN", "AR"], "I": [["I", "Laelia jongheana", 9, 0, 171], ["I", "Laelia lobata", 9, 0, 126], ["I", "Megaptera novaeangliae", 3, 0, 104], ["I", "Panthera onca", 3, 0, 21], ["I", "Puma yagouaroundi", 3, 0, 3], ["I", "Brachyteles arachnoides", 2, 0, 9], ["I", "Harpia harpyja", 2, 0, 2]], "II": [["II", "Cattleya spp.", 30, 0, 24899], ["II", "Oncidium spp.", 21, 5, 2067], ["II", "Cattleya intermedia", 20, 0, 1364], ["II", "Laelia purpurata", 20, 0, 3099], ["II", "Cattleya labiata", 19, 0, 2241], ["II", "Cattleya loddigesii", 18, 0, 1011], ["II", "Python reticulatus", 16, 13532, 351]], "III": [["III", "Swietenia macrophylla", 45, 19, 42019], ["III", "Crotalus durissus", 6, 0, 85], ["III", "Pteroglossus castanotis", 2, 0, 2], ["III", "Baillonius bailloni", 1, 0, 2], ["III", "Cairina moschata", 1, 0, 280], ["III", "Nasua nasua", 1, 0, 1], ["III", "Ramphastos dicolorus", 1, 0, 0]], "N": [["N", "Hippocampus kuda", 4, 0, 0], ["N", "Hippocampus spp.", 4, 0, 0], ["N", "Hippocampus erectus", 3, 0, 0], ["N", "Hippocampus reidi", 3, 0, 0], ["N", "Hippocampus coronatus", 1, 0, 0]], "Purpose": [["T", 1623], ["S", 57], ["E", 29], ["Z", 23], ["P", 17], ["Q", 5], ["B", 3], [null, 0]], "coord": [-55.0, -10.0], "nameCN": "\u5df4\u897f", "export_tgt_info": [{"name": "\u7f8e\u56fd", "coord": [-97.0, 38.0]}, {"name": "\u5fb7\u56fd", "coord": [9.0, 51.0]}, {"name": "\u65e5\u672c", "coord": [138.0, 36.0]}, {"name": "\u82f1\u56fd", "coord": [-2.0, 54.0]}, {"name": "\u745e\u58eb", "coord": [8.0, 47.0]}, {"name": "\u9999\u6e2f\u7279\u522b\u884c\u653f\u533a", "coord": [114.1667, 22.25]}, {"name": "\u52a0\u62ff\u5927", "coord": [-95.0, 60.0]}, {"name": "\u6cd5\u56fd", "coord": [2.0, 46.0]}, {"name": "\u5965\u5730\u5229", "coord": [13.3333, 47.3333]}, {"name": "\u8461\u8404\u7259", "coord": [-8.0, 39.5]}, {"name": "\u610f\u5927\u5229", "coord": [12.8333, 42.8333]}, {"name": "\u59d4\u5185\u745e\u62c9", "coord": [-66.0, 8.0]}, {"name": "\u667a\u5229", "coord": [-71.0, -30.0]}, {"name": "\u6fb3\u5927\u5229\u4e9a", "coord": [133.0, -27.0]}, {"name": "\u897f\u73ed\u7259", "coord": [-4.0, 40.0]}, {"name": "\u53f0\u6e7e\u7701", "coord": [121.0, 23.5]}, {"name": "\u4e4c\u62c9\u572d", "coord": [-56.0, -33.0]}, {"name": "\u5384\u74dc\u591a\u5c14", "coord": [-77.5, -2.0]}, {"name": "\u672a\u77e5", "coord": [0, 0]}, {"name": "\u963f\u6839\u5ef7", "coord": [-64.0, -34.0]}], "purpose_info": [["\u5546\u4e1a", 1623], ["\u79d1\u7814", 57], ["\u7528\u4e8e\u6559\u80b2", 29], ["\u52a8\u7269\u56ed", 23], ["\u4e2a\u4eba", 17], ["\u9a6c\u620f\u548c\u5de1\u56de\u5c55\u89c8", 5], ["\u5708\u517b\u7e41\u6b96\u6216\u4eba\u5de5\u7e41\u6b96", 3], ["\u672a\u77e5", 0]]}, {"name": "TH", "num": 1810, "export_tgt": ["US", "JP", "DE", "CZ", "GB", "HK", "ES", "IT", "BE", "CA", "CH", "LK", "CN", "BS", "AN", "AU", "NL", "TW", "ZA", "BR"], "I": [["I", "Crocodylus siamensis", 125, 2133, 46542], ["I", "Crocodylus hybrid", 19, 0, 237], ["I", "Vanda coerulea", 15, 0, 257], ["I", "Elephas maximus", 9, 4, 315], ["I", "Dendrobium cruentum", 8, 0, 164], ["I", "Paphiopedilum concolor", 8, 0, 159], ["I", "Paphiopedilum godefroyae", 8, 0, 1501]], "II": [["II", "Rhynchostylis gigantea", 44, 0, 17739], ["II", "Rhynchostylis coelestis", 32, 0, 4395], ["II", "Phalaenopsis spp.", 29, 200, 352], ["II", "Phalaenopsis pulcherrima", 27, 0, 1341], ["II", "Dendrobium spp.", 26, 180, 30], ["II", "Caiman crocodilus fuscus", 25, 167039, 58652], ["II", "Brassavola nodosa", 24, 0, 1958]], "III": [["III", "Daboia russelii", 2, 0, 0], ["III", "Odobenus rosmarus", 1, 0, 0]], "N": [["N", "Homalopsis buccata", 5, 0, 0], ["N", "Enhydris bocourti", 2, 0, 0], ["N", "Acrochordus javanicus", 1, 0, 0], ["N", "Hippocampus kuda", 1, 0, 0]], "Purpose": [["T", 510], ["P", 109], ["B", 39], ["G", 31], ["S", 14], ["Q", 13], ["E", 3], ["Z", 3], [null, 0]], "coord": [100.0, 15.0], "nameCN": "\u6cf0\u56fd", "export_tgt_info": [{"name": "\u7f8e\u56fd", "coord": [-97.0, 38.0]}, {"name": "\u65e5\u672c", "coord": [138.0, 36.0]}, {"name": "\u5fb7\u56fd", "coord": [9.0, 51.0]}, {"name": "\u6377\u514b", "coord": [15.5, 49.75]}, {"name": "\u82f1\u56fd", "coord": [-2.0, 54.0]}, {"name": "\u9999\u6e2f\u7279\u522b\u884c\u653f\u533a", "coord": [114.1667, 22.25]}, {"name": "\u897f\u73ed\u7259", "coord": [-4.0, 40.0]}, {"name": "\u610f\u5927\u5229", "coord": [12.8333, 42.8333]}, {"name": "\u6bd4\u5229\u65f6", "coord": [4.0, 50.8333]}, {"name": "\u52a0\u62ff\u5927", "coord": [-95.0, 60.0]}, {"name": "\u745e\u58eb", "coord": [8.0, 47.0]}, {"name": "\u65af\u91cc\u5170\u5361", "coord": [81.0, 7.0]}, {"name": "\u4e2d\u56fd", "coord": [105.0, 35.0]}, {"name": "\u5df4\u54c8\u9a6c", "coord": [-76.0, 24.25]}, {"name": "\u672a\u77e5", "coord": [0, 0]}, {"name": "\u6fb3\u5927\u5229\u4e9a", "coord": [133.0, -27.0]}, {"name": "\u8377\u5170", "coord": [5.75, 52.5]}, {"name": "\u53f0\u6e7e\u7701", "coord": [121.0, 23.5]}, {"name": "\u5357\u975e", "coord": [24.0, -29.0]}, {"name": "\u5df4\u897f", "coord": [-55.0, -10.0]}], "purpose_info": [["\u5546\u4e1a", 510], ["\u4e2a\u4eba", 109], ["\u5708\u517b\u7e41\u6b96\u6216\u4eba\u5de5\u7e41\u6b96", 39], ["\u690d\u7269\u56ed", 31], ["\u79d1\u7814", 14], ["\u9a6c\u620f\u548c\u5de1\u56de\u5c55\u89c8", 13], ["\u7528\u4e8e\u6559\u80b2", 3], ["\u52a8\u7269\u56ed", 3], ["\u672a\u77e5", 0]]}, {"name": "MX", "num": 1612, "export_tgt": ["US", "CA", "GB", "FR", "ES", "CH", "NO", "DE", "CN", "BR", "IT", "JP", "PA", "GT", "CO", "CR", "SV", "ZA", "AR", "AT"], "I": [["I", "Crocodylus moreletii", 22, 0, 1860], ["I", "Cheloniidae spp.", 12, 0, 0], ["I", "Panthera tigris", 10, 7, 25], ["I", "Pan troglodytes", 8, 7, 5], ["I", "Loxodonta africana", 7, 113, 51], ["I", "Panthera onca", 6, 1, 8], ["I", "Elephantidae spp.", 5, 8, 0]], "II": [["II", "Python reticulatus", 67, 38498, 45652], ["II", "Caiman crocodilus fuscus", 47, 255740, 192748], ["II", "Crocodylus niloticus", 39, 11758, 12889], ["II", "Varanus salvator", 31, 179253, 77445], ["II", "Alligator mississippiensis", 23, 50041, 20471], ["II", "Python curtus", 23, 16968, 17465], ["II", "Python bivittatus", 21, 7835, 10008]], "III": [["III", "Anatidae spp.", 3, 0, 0], ["III", "Daboia russelii", 3, 0, 0], ["III", "Anas acuta", 2, 0, 0], ["III", "Anas crecca", 2, 0, 0], ["III", "Crotalus durissus", 2, 0, 1], ["III", "Meleagris ocellata", 2, 0, 13], ["III", "Swietenia macrophylla", 2, 622, 12636]], "N": [], "Purpose": [["T", 1134], ["P", 218], ["S", 85], ["Q", 48], ["H", 18], ["B", 17], ["Z", 17], ["M", 1], [null, 0]], "coord": [-102.0, 23.0], "nameCN": "\u58a8\u897f\u54e5", "export_tgt_info": [{"name": "\u7f8e\u56fd", "coord": [-97.0, 38.0]}, {"name": "\u52a0\u62ff\u5927", "coord": [-95.0, 60.0]}, {"name": "\u82f1\u56fd", "coord": [-2.0, 54.0]}, {"name": "\u6cd5\u56fd", "coord": [2.0, 46.0]}, {"name": "\u897f\u73ed\u7259", "coord": [-4.0, 40.0]}, {"name": "\u745e\u58eb", "coord": [8.0, 47.0]}, {"name": "\u632a\u5a01", "coord": [10.0, 62.0]}, {"name": "\u5fb7\u56fd", "coord": [9.0, 51.0]}, {"name": "\u4e2d\u56fd", "coord": [105.0, 35.0]}, {"name": "\u5df4\u897f", "coord": [-55.0, -10.0]}, {"name": "\u610f\u5927\u5229", "coord": [12.8333, 42.8333]}, {"name": "\u65e5\u672c", "coord": [138.0, 36.0]}, {"name": "\u5df4\u62ff\u9a6c", "coord": [-80.0, 9.0]}, {"name": "\u5371\u5730\u9a6c\u62c9", "coord": [-90.25, 15.5]}, {"name": "\u54e5\u4f26\u6bd4\u4e9a", "coord": [-72.0, 4.0]}, {"name": "\u54e5\u65af\u8fbe\u9ece\u52a0", "coord": [-84.0, 10.0]}, {"name": "\u8428\u5c14\u74e6\u591a", "coord": [-88.9167, 13.8333]}, {"name": "\u5357\u975e", "coord": [24.0, -29.0]}, {"name": "\u963f\u6839\u5ef7", "coord": [-64.0, -34.0]}, {"name": "\u5965\u5730\u5229", "coord": [13.3333, 47.3333]}], "purpose_info": [["\u5546\u4e1a", 1134], ["\u4e2a\u4eba", 218], ["\u79d1\u7814", 85], ["\u9a6c\u620f\u548c\u5de1\u56de\u5c55\u89c8", 48], ["\u6218\u5229\u6027\u72e9\u730e", 18], ["\u5708\u517b\u7e41\u6b96\u6216\u4eba\u5de5\u7e41\u6b96", 17], ["\u52a8\u7269\u56ed", 17], ["\u533b\u836f(\u5305\u62ec\u751f\u7269\u533b\u836f\u7814\u7a76)", 1], ["\u672a\u77e5", 0]]}, {"name": "GB", "num": 1555, "export_tgt": ["US", "JP", "CA", "CH", "CY", "JE", "ZA", "MT", "AU", "IL", "IS", "BB", "CN", "NZ", "AE", "TW", "IM", "CZ", "SG", "QA"], "I": [["I", "Elephas maximus", 37, 116, 967], ["I", "Cheloniidae spp.", 36, 12, 216], ["I", "Dalbergia nigra", 16, 0, 628], ["I", "Eretmochelys imbricata", 13, 38, 36], ["I", "Rhinocerotidae spp.", 13, 1, 21], ["I", "Elephantidae spp.", 11, 158, 0], ["I", "Falco peregrinus", 11, 7, 15]], "II": [["II", "Loxodonta africana", 97, 744, 4337], ["II", "Macaca fascicularis", 62, 11251, 25828], ["II", "Alligator mississippiensis", 61, 27969, 4099], ["II", "Python reticulatus", 52, 2856, 1813], ["II", "Psittacus erithacus", 38, 1363, 246], ["II", "Acipenser stellatus", 17, 1461, 6289], ["II", "Amazona aestiva", 14, 76, 13]], "III": [["III", "Odobenus rosmarus", 13, 18, 65], ["III", "Psittacula krameri", 13, 115, 88], ["III", "Antilope cervicapra", 6, 1, 4], ["III", "Anas crecca", 4, 0, 387], ["III", "Columba livia", 4, 0, 1], ["III", "Uraeginthus bengalus", 4, 0, 68], ["III", "Anas clypeata", 3, 0, 1]], "N": [], "Purpose": [["T", 859], ["P", 301], ["B", 62], ["S", 58], ["Z", 47], ["Q", 37], ["M", 32], ["E", 19], ["H", 12], ["G", 2], ["N", 1], [null, 0]], "coord": [-2.0, 54.0], "nameCN": "\u82f1\u56fd", "export_tgt_info": [{"name": "\u7f8e\u56fd", "coord": [-97.0, 38.0]}, {"name": "\u65e5\u672c", "coord": [138.0, 36.0]}, {"name": "\u52a0\u62ff\u5927", "coord": [-95.0, 60.0]}, {"name": "\u745e\u58eb", "coord": [8.0, 47.0]}, {"name": "\u585e\u6d66\u8def\u65af", "coord": [33.0, 35.0]}, {"name": "\u6cfd\u897f\u5c9b", "coord": [-2.13, 49.21]}, {"name": "\u5357\u975e", "coord": [24.0, -29.0]}, {"name": "\u9a6c\u8033\u4ed6", "coord": [14.5833, 35.8333]}, {"name": "\u6fb3\u5927\u5229\u4e9a", "coord": [133.0, -27.0]}, {"name": "\u4ee5\u8272\u5217", "coord": [34.75, 31.5]}, {"name": "\u51b0\u5c9b", "coord": [-18.0, 65.0]}, {"name": "\u5df4\u5df4\u591a\u65af", "coord": [-59.5333, 13.1667]}, {"name": "\u4e2d\u56fd", "coord": [105.0, 35.0]}, {"name": "\u65b0\u897f\u5170", "coord": [174.0, -41.0]}, {"name": "\u963f\u62c9\u4f2f\u8054\u5408\u914b\u957f\u56fd", "coord": [54.0, 24.0]}, {"name": "\u53f0\u6e7e\u7701", "coord": [121.0, 23.5]}, {"name": "\u9a6c\u6069\u5c9b", "coord": [-4.55, 54.23]}, {"name": "\u6377\u514b", "coord": [15.5, 49.75]}, {"name": "\u65b0\u52a0\u5761", "coord": [103.8, 1.3667]}, {"name": "\u5361\u5854\u5c14", "coord": [51.25, 25.5]}], "purpose_info": [["\u5546\u4e1a", 859], ["\u4e2a\u4eba", 301], ["\u5708\u517b\u7e41\u6b96\u6216\u4eba\u5de5\u7e41\u6b96", 62], ["\u79d1\u7814", 58], ["\u52a8\u7269\u56ed", 47], ["\u9a6c\u620f\u548c\u5de1\u56de\u5c55\u89c8", 37], ["\u533b\u836f(\u5305\u62ec\u751f\u7269\u533b\u836f\u7814\u7a76)", 32], ["\u7528\u4e8e\u6559\u80b2", 19], ["\u6218\u5229\u6027\u72e9\u730e", 12], ["\u690d\u7269\u56ed", 2], ["\u91cd\u65b0\u5f15\u5165\u6216\u5f15\u5165\u91ce\u5916", 1], ["\u672a\u77e5", 0]]}, {"name": "CO", "num": 1412, "export_tgt": ["US", "CH", "DE", "PA", "GB", "JP", "AU", "EC", "VE", "TW", "MX", "FR", "IT", "SG", "ES", "CR", "TH", "BE", "AN", "CA"], "I": [["I", "Panthera tigris", 3, 2, 9], ["I", "Elephas maximus", 2, 0, 9], ["I", "Loxodonta africana", 2, 0, 3], ["I", "Pan troglodytes", 2, 0, 1], ["I", "Cacatua moluccensis", 1, 0, 1], ["I", "Mandrillus sphinx", 1, 0, 1], ["I", "Psittacidae spp.", 1, 0, 2]], "II": [["II", "Caiman crocodilus fuscus", 60, 1178, 1088256], ["II", "Cattleya spp.", 13, 4, 795], ["II", "Maxillaria spp.", 10, 0, 303], ["II", "Oncidium spp.", 10, 2, 287], ["II", "Lepanthes spp.", 9, 0, 579], ["II", "Odontoglossum spp.", 9, 0, 262], ["II", "Paphinia spp.", 9, 0, 142]], "III": [], "N": [], "Purpose": [["T", 1294], ["Q", 12], ["P", 9], ["E", 2], ["H", 1], ["S", 1], ["Z", 1], [null, 0]], "coord": [-72.0, 4.0], "nameCN": "\u54e5\u4f26\u6bd4\u4e9a", "export_tgt_info": [{"name": "\u7f8e\u56fd", "coord": [-97.0, 38.0]}, {"name": "\u745e\u58eb", "coord": [8.0, 47.0]}, {"name": "\u5fb7\u56fd", "coord": [9.0, 51.0]}, {"name": "\u5df4\u62ff\u9a6c", "coord": [-80.0, 9.0]}, {"name": "\u82f1\u56fd", "coord": [-2.0, 54.0]}, {"name": "\u65e5\u672c", "coord": [138.0, 36.0]}, {"name": "\u6fb3\u5927\u5229\u4e9a", "coord": [133.0, -27.0]}, {"name": "\u5384\u74dc\u591a\u5c14", "coord": [-77.5, -2.0]}, {"name": "\u59d4\u5185\u745e\u62c9", "coord": [-66.0, 8.0]}, {"name": "\u53f0\u6e7e\u7701", "coord": [121.0, 23.5]}, {"name": "\u58a8\u897f\u54e5", "coord": [-102.0, 23.0]}, {"name": "\u6cd5\u56fd", "coord": [2.0, 46.0]}, {"name": "\u610f\u5927\u5229", "coord": [12.8333, 42.8333]}, {"name": "\u65b0\u52a0\u5761", "coord": [103.8, 1.3667]}, {"name": "\u897f\u73ed\u7259", "coord": [-4.0, 40.0]}, {"name": "\u54e5\u65af\u8fbe\u9ece\u52a0", "coord": [-84.0, 10.0]}, {"name": "\u6cf0\u56fd", "coord": [100.0, 15.0]}, {"name": "\u6bd4\u5229\u65f6", "coord": [4.0, 50.8333]}, {"name": "\u672a\u77e5", "coord": [0, 0]}, {"name": "\u52a0\u62ff\u5927", "coord": [-95.0, 60.0]}], "purpose_info": [["\u5546\u4e1a", 1294], ["\u9a6c\u620f\u548c\u5de1\u56de\u5c55\u89c8", 12], ["\u4e2a\u4eba", 9], ["\u7528\u4e8e\u6559\u80b2", 2], ["\u6218\u5229\u6027\u72e9\u730e", 1], ["\u79d1\u7814", 1], ["\u52a8\u7269\u56ed", 1], ["\u672a\u77e5", 0]]}, {"name": "ES", "num": 1405, "export_tgt": ["CH", "US", "AR", "JP", "CZ", "IL", "CL", "HK", "DO", "CN", "VE", "AE", "BR", "CA", "MX", "CU", "TW", "AU", "MA", "ZA"], "I": [["I", "Dalbergia nigra", 19, 1, 9222], ["I", "Falco hybrid", 6, 4, 18], ["I", "Falco peregrinus", 4, 4, 277], ["I", "Caloenas nicobarica", 3, 6, 12], ["I", "Elephas maximus", 3, 43, 3], ["I", "Eretmochelys imbricata", 3, 0, 12], ["I", "Lynx pardinus", 3, 0, 281]], "II": [["II", "Python reticulatus", 105, 48973, 43643], ["II", "Alligator mississippiensis", 57, 2124, 29798], ["II", "Python sebae", 40, 11050, 4680], ["II", "Caiman crocodilus crocodilus", 39, 10670, 31646], ["II", "Varanus niloticus", 35, 29948, 26453], ["II", "Caiman crocodilus fuscus", 33, 253017, 22719], ["II", "Tupinambis spp.", 32, 56536, 47548]], "III": [["III", "Odobenus rosmarus", 11, 17, 14], ["III", "Amadina fasciata", 6, 27135, 1170], ["III", "Estrilda melpoda", 6, 11500, 740], ["III", "Serinus mozambicus", 6, 33930, 760], ["III", "Psittacula krameri", 5, 14210, 45], ["III", "Uraeginthus bengalus", 5, 24980, 320], ["III", "Vidua macroura", 5, 1750, 180]], "N": [], "Purpose": [["T", 1076], ["P", 39], ["S", 23], ["E", 17], ["H", 11], ["Z", 9], ["B", 7], ["Q", 7], ["M", 2], [null, 0]], "coord": [-4.0, 40.0], "nameCN": "\u897f\u73ed\u7259", "export_tgt_info": [{"name": "\u745e\u58eb", "coord": [8.0, 47.0]}, {"name": "\u7f8e\u56fd", "coord": [-97.0, 38.0]}, {"name": "\u963f\u6839\u5ef7", "coord": [-64.0, -34.0]}, {"name": "\u65e5\u672c", "coord": [138.0, 36.0]}, {"name": "\u6377\u514b", "coord": [15.5, 49.75]}, {"name": "\u4ee5\u8272\u5217", "coord": [34.75, 31.5]}, {"name": "\u667a\u5229", "coord": [-71.0, -30.0]}, {"name": "\u9999\u6e2f\u7279\u522b\u884c\u653f\u533a", "coord": [114.1667, 22.25]}, {"name": "\u591a\u7c73\u5c3c\u52a0\u5171\u548c\u56fd", "coord": [-70.6667, 19.0]}, {"name": "\u4e2d\u56fd", "coord": [105.0, 35.0]}, {"name": "\u59d4\u5185\u745e\u62c9", "coord": [-66.0, 8.0]}, {"name": "\u963f\u62c9\u4f2f\u8054\u5408\u914b\u957f\u56fd", "coord": [54.0, 24.0]}, {"name": "\u5df4\u897f", "coord": [-55.0, -10.0]}, {"name": "\u52a0\u62ff\u5927", "coord": [-95.0, 60.0]}, {"name": "\u58a8\u897f\u54e5", "coord": [-102.0, 23.0]}, {"name": "\u53e4\u5df4", "coord": [-80.0, 21.5]}, {"name": "\u53f0\u6e7e\u7701", "coord": [121.0, 23.5]}, {"name": "\u6fb3\u5927\u5229\u4e9a", "coord": [133.0, -27.0]}, {"name": "\u6469\u6d1b\u54e5", "coord": [-5.0, 32.0]}, {"name": "\u5357\u975e", "coord": [24.0, -29.0]}], "purpose_info": [["\u5546\u4e1a", 1076], ["\u4e2a\u4eba", 39], ["\u79d1\u7814", 23], ["\u7528\u4e8e\u6559\u80b2", 17], ["\u6218\u5229\u6027\u72e9\u730e", 11], ["\u52a8\u7269\u56ed", 9], ["\u5708\u517b\u7e41\u6b96\u6216\u4eba\u5de5\u7e41\u6b96", 7], ["\u9a6c\u620f\u548c\u5de1\u56de\u5c55\u89c8", 7], ["\u533b\u836f(\u5305\u62ec\u751f\u7269\u533b\u836f\u7814\u7a76)", 2], ["\u672a\u77e5", 0]]}, {"name": "ZW", "num": 1291, "export_tgt": ["US", "DE", "ZA", "PT", "ES", "FR", "AT", "CA", "GB", "IT", "DK", "NO", "JP", "BW", "PL", "MX", "CH", "CN", "AR", "AU"], "I": [["I", "Panthera pardus", 110, 7, 1565], ["I", "Acinonyx jubatus", 16, 1, 8], ["I", "Ceratotherium simum", 3, 0, 1], ["I", "Diceros bicornis", 3, 1, 0], ["I", "Dendrobium cruentum", 2, 0, 0]], "II": [["II", "Loxodonta africana", 336, 42, 18788], ["II", "Crocodylus niloticus", 160, 1619, 159076], ["II", "Hippopotamus amphibius", 125, 416, 4080], ["II", "Papio ursinus", 90, 0, 475], ["II", "Panthera leo", 78, 5, 430], ["II", "Leptailurus serval", 34, 0, 63], ["II", "Felis silvestris", 32, 1, 81]], "III": [["III", "Damaliscus lunatus", 84, 2, 354], ["III", "Civettictis civetta", 37, 0, 118], ["III", "Mellivora capensis", 11, 0, 14], ["III", "Alopochen aegyptiaca", 4, 0, 0], ["III", "Treron calvus", 2, 0, 2], ["III", "Columba guinea", 1, 0, 2], ["III", "Nettapus auritus", 1, 0, 0]], "N": [], "Purpose": [["T", 792], ["H", 272], ["P", 151], ["B", 9], ["Q", 4], ["E", 2], [null, 0]], "coord": [30.0, -20.0], "nameCN": "\u6d25\u5df4\u5e03\u97e6", "export_tgt_info": [{"name": "\u7f8e\u56fd", "coord": [-97.0, 38.0]}, {"name": "\u5fb7\u56fd", "coord": [9.0, 51.0]}, {"name": "\u5357\u975e", "coord": [24.0, -29.0]}, {"name": "\u8461\u8404\u7259", "coord": [-8.0, 39.5]}, {"name": "\u897f\u73ed\u7259", "coord": [-4.0, 40.0]}, {"name": "\u6cd5\u56fd", "coord": [2.0, 46.0]}, {"name": "\u5965\u5730\u5229", "coord": [13.3333, 47.3333]}, {"name": "\u52a0\u62ff\u5927", "coord": [-95.0, 60.0]}, {"name": "\u82f1\u56fd", "coord": [-2.0, 54.0]}, {"name": "\u610f\u5927\u5229", "coord": [12.8333, 42.8333]}, {"name": "\u4e39\u9ea6", "coord": [10.0, 56.0]}, {"name": "\u632a\u5a01", "coord": [10.0, 62.0]}, {"name": "\u65e5\u672c", "coord": [138.0, 36.0]}, {"name": "\u535a\u8328\u74e6\u7eb3", "coord": [24.0, -22.0]}, {"name": "\u6ce2\u5170", "coord": [20.0, 52.0]}, {"name": "\u58a8\u897f\u54e5", "coord": [-102.0, 23.0]}, {"name": "\u745e\u58eb", "coord": [8.0, 47.0]}, {"name": "\u4e2d\u56fd", "coord": [105.0, 35.0]}, {"name": "\u963f\u6839\u5ef7", "coord": [-64.0, -34.0]}, {"name": "\u6fb3\u5927\u5229\u4e9a", "coord": [133.0, -27.0]}], "purpose_info": [["\u5546\u4e1a", 792], ["\u6218\u5229\u6027\u72e9\u730e", 272], ["\u4e2a\u4eba", 151], ["\u5708\u517b\u7e41\u6b96\u6216\u4eba\u5de5\u7e41\u6b96", 9], ["\u9a6c\u620f\u548c\u5de1\u56de\u5c55\u89c8", 4], ["\u7528\u4e8e\u6559\u80b2", 2], ["\u672a\u77e5", 0]]}, {"name": "MG", "num": 1159, "export_tgt": ["US", "FR", "JP", "BE", "DE", "IT", "CH", "GB", "ZA", "NL", "ES", "CA", "HU", "JE", "TH", "RE", "RU", "XX", "CN", "MU"], "I": [["I", "Prolemur simus", 10, 0, 178], ["I", "Microcebus murinus", 6, 35, 378], ["I", "Varecia variegata", 6, 4, 49], ["I", "Avahi laniger", 5, 0, 28], ["I", "Hapalemur aureus", 5, 0, 24], ["I", "Hapalemur griseus", 5, 0, 62], ["I", "Indri indri", 5, 0, 29]], "II": [["II", "Crocodylus niloticus", 51, 0, 9238], ["II", "Cymbidiella spp.", 17, 0, 55], ["II", "Furcifer pardalis", 14, 0, 3597], ["II", "Jumellea spp.", 14, 0, 65], ["II", "Erymnochelys madagascariensis", 13, 0, 582], ["II", "Furcifer oustaleti", 13, 0, 1254], ["II", "Mantella aurantiaca", 12, 0, 11522]], "III": [["III", "Pelusios castaneus", 2, 0, 101], ["III", "Pelomedusa subrufa", 1, 0, 60]], "N": [["N", "Mantella betsileo", 9, 0, 1335], ["N", "Mantella spp.", 6, 0, 2011], ["N", "Brookesia superciliaris", 3, 0, 0], ["N", "Uroplatus henkeli", 3, 0, 0], ["N", "Uroplatus phantasticus", 3, 0, 0], ["N", "Brookesia ebenaui", 2, 0, 0], ["N", "Brookesia minima", 2, 0, 0], ["N", "Brookesia stumpffi", 2, 0, 0]], "Purpose": [["T", 578], ["P", 311], ["S", 188], ["Q", 31], ["B", 3], ["G", 2], [null, 0]], "coord": [47.0, -20.0], "nameCN": "\u9a6c\u8fbe\u52a0\u65af\u52a0", "export_tgt_info": [{"name": "\u7f8e\u56fd", "coord": [-97.0, 38.0]}, {"name": "\u6cd5\u56fd", "coord": [2.0, 46.0]}, {"name": "\u65e5\u672c", "coord": [138.0, 36.0]}, {"name": "\u6bd4\u5229\u65f6", "coord": [4.0, 50.8333]}, {"name": "\u5fb7\u56fd", "coord": [9.0, 51.0]}, {"name": "\u610f\u5927\u5229", "coord": [12.8333, 42.8333]}, {"name": "\u745e\u58eb", "coord": [8.0, 47.0]}, {"name": "\u82f1\u56fd", "coord": [-2.0, 54.0]}, {"name": "\u5357\u975e", "coord": [24.0, -29.0]}, {"name": "\u8377\u5170", "coord": [5.75, 52.5]}, {"name": "\u897f\u73ed\u7259", "coord": [-4.0, 40.0]}, {"name": "\u52a0\u62ff\u5927", "coord": [-95.0, 60.0]}, {"name": "\u5308\u7259\u5229", "coord": [20.0, 47.0]}, {"name": "\u6cfd\u897f\u5c9b", "coord": [-2.13, 49.21]}, {"name": "\u6cf0\u56fd", "coord": [100.0, 15.0]}, {"name": "\u7559\u5c3c\u6c6a", "coord": [55.6, -21.1]}, {"name": "\u4fc4\u7f57\u65af", "coord": [100.0, 60.0]}, {"name": "\u672a\u77e5", "coord": [0, 0]}, {"name": "\u4e2d\u56fd", "coord": [105.0, 35.0]}, {"name": "\u6bdb\u91cc\u6c42\u65af", "coord": [57.55, -20.2833]}], "purpose_info": [["\u5546\u4e1a", 578], ["\u4e2a\u4eba", 311], ["\u79d1\u7814", 188], ["\u9a6c\u620f\u548c\u5de1\u56de\u5c55\u89c8", 31], ["\u5708\u517b\u7e41\u6b96\u6216\u4eba\u5de5\u7e41\u6b96", 3], ["\u690d\u7269\u56ed", 2], ["\u672a\u77e5", 0]]}, {"name": "BE", "num": 1146, "export_tgt": ["IL", "JP", "CH", "US", "TR", "NO", "MT", "TW", "AE", "PL", "MX", "TN", "ZA", "HU", "KR", "AR", "CA", "ID", "SG", "BH"], "I": [["I", "Loxodonta africana", 25, 98, 103], ["I", "Elephantidae spp.", 12, 30, 33], ["I", "Falco hybrid", 9, 7, 47], ["I", "Panthera tigris", 7, 0, 12], ["I", "Lophophorus impejanus", 6, 0, 14], ["I", "Syrmaticus humiae", 5, 0, 9], ["I", "Panthera pardus", 4, 12, 3]], "II": [["II", "Platycercus eximius", 23, 0, 1096], ["II", "Psittacus erithacus", 22, 4243, 305], ["II", "Platycercus elegans", 17, 0, 350], ["II", "Psephotus haematonotus", 15, 0, 1199], ["II", "Alligator mississippiensis", 11, 4021, 356], ["II", "Neophema pulchella", 11, 0, 242], ["II", "Agapornis roseicollis", 10, 1402, 345]], "III": [["III", "Psittacula krameri", 23, 504, 1410], ["III", "Serinus mozambicus", 14, 3710, 6486], ["III", "Uraeginthus bengalus", 12, 3330, 1820], ["III", "Vidua macroura", 11, 230, 2459], ["III", "Amadina fasciata", 10, 2570, 1177], ["III", "Euplectes franciscanus", 9, 0, 2050], ["III", "Amandava subflava", 7, 150, 540]], "N": [["N", "Lophura diardi", 3, 0, 10], ["N", "Lophura leucomelanos", 3, 0, 22], ["N", "Trachemys scripta elegans", 1, 0, 1]], "Purpose": [["T", 947], ["P", 71], ["B", 40], ["Z", 38], ["E", 12], ["L", 8], ["Q", 8], ["M", 2], ["S", 2], ["H", 1], ["N", 1], [null, 0]], "coord": [4.0, 50.8333], "nameCN": "\u6bd4\u5229\u65f6", "export_tgt_info": [{"name": "\u4ee5\u8272\u5217", "coord": [34.75, 31.5]}, {"name": "\u65e5\u672c", "coord": [138.0, 36.0]}, {"name": "\u745e\u58eb", "coord": [8.0, 47.0]}, {"name": "\u7f8e\u56fd", "coord": [-97.0, 38.0]}, {"name": "\u571f\u8033\u5176", "coord": [35.0, 39.0]}, {"name": "\u632a\u5a01", "coord": [10.0, 62.0]}, {"name": "\u9a6c\u8033\u4ed6", "coord": [14.5833, 35.8333]}, {"name": "\u53f0\u6e7e\u7701", "coord": [121.0, 23.5]}, {"name": "\u963f\u62c9\u4f2f\u8054\u5408\u914b\u957f\u56fd", "coord": [54.0, 24.0]}, {"name": "\u6ce2\u5170", "coord": [20.0, 52.0]}, {"name": "\u58a8\u897f\u54e5", "coord": [-102.0, 23.0]}, {"name": "\u7a81\u5c3c\u65af", "coord": [9.0, 34.0]}, {"name": "\u5357\u975e", "coord": [24.0, -29.0]}, {"name": "\u5308\u7259\u5229", "coord": [20.0, 47.0]}, {"name": "\u97e9\u56fd", "coord": [127.5, 37.0]}, {"name": "\u963f\u6839\u5ef7", "coord": [-64.0, -34.0]}, {"name": "\u52a0\u62ff\u5927", "coord": [-95.0, 60.0]}, {"name": "\u5370\u5ea6\u5c3c\u897f\u4e9a", "coord": [120.0, -5.0]}, {"name": "\u65b0\u52a0\u5761", "coord": [103.8, 1.3667]}, {"name": "\u5df4\u6797", "coord": [50.55, 26.0]}], "purpose_info": [["\u5546\u4e1a", 947], ["\u4e2a\u4eba", 71], ["\u5708\u517b\u7e41\u6b96\u6216\u4eba\u5de5\u7e41\u6b96", 40], ["\u52a8\u7269\u56ed", 38], ["\u7528\u4e8e\u6559\u80b2", 12], ["\u6267\u6cd5/\u53f8\u6cd5/\u6cd5\u533b", 8], ["\u9a6c\u620f\u548c\u5de1\u56de\u5c55\u89c8", 8], ["\u533b\u836f(\u5305\u62ec\u751f\u7269\u533b\u836f\u7814\u7a76)", 2], ["\u79d1\u7814", 2], ["\u6218\u5229\u6027\u72e9\u730e", 1], ["\u91cd\u65b0\u5f15\u5165\u6216\u5f15\u5165\u91ce\u5916", 1], ["\u672a\u77e5", 0]]}, {"name": "SG", "num": 975, "export_tgt": ["JP", "US", "HK", "IT", "NL", "TW", "KR", "MY", "CN", "DE", "CH", "MX", "GB", "ES", "FR", "ZA", "CA", "AU", "AE", "LK"], "I": [["I", "Cacatua moluccensis", 8, 0, 79], ["I", "Caloenas nicobarica", 3, 0, 62], ["I", "Neofelis nebulosa", 3, 0, 3], ["I", "Panthera pardus", 3, 2, 3], ["I", "Panthera tigris", 3, 42, 3], ["I", "Buceros bicornis", 2, 0, 2], ["I", "Eretmochelys imbricata", 2, 0, 1]], "II": [["II", "Crocodylus niloticus", 114, 40959, 59034], ["II", "Alligator mississippiensis", 69, 58932, 47159], ["II", "Crocodylus porosus", 48, 10589, 2132], ["II", "Python reticulatus", 46, 309236, 350107], ["II", "Scleropages formosus", 44, 10498, 3383], ["II", "Caiman crocodilus fuscus", 39, 357424, 328792], ["II", "Varanus salvator", 36, 428628, 529023]], "III": [["III", "Arctictis binturong", 2, 0, 0], ["III", "Amandava subflava", 1, 40, 0], ["III", "Columba livia", 1, 0, 0], ["III", "Daboia russelii", 1, 0, 10000], ["III", "Estrilda melpoda", 1, 0, 0], ["III", "Lagonosticta senegala", 1, 0, 0], ["III", "Musophaga violacea", 1, 100, 0]], "N": [["N", "Hippocampus kuda", 5, 0, 0], ["N", "Hippocampus trimaculatus", 5, 0, 0], ["N", "Homalopsis buccata", 4, 0, 0], ["N", "Hippocampus spp.", 3, 0, 0], ["N", "Acrochordus javanicus", 2, 93, 0], ["N", "Elaphe radiata", 1, 0, 0], ["N", "Hippocampus coronatus", 1, 0, 0], ["N", "Hippocampus hippocampus", 1, 0, 0]], "Purpose": [["T", 684], ["P", 65], ["Z", 40], ["S", 37], ["B", 8], ["Q", 6], [null, 0]], "coord": [103.8, 1.3667], "nameCN": "\u65b0\u52a0\u5761", "export_tgt_info": [{"name": "\u65e5\u672c", "coord": [138.0, 36.0]}, {"name": "\u7f8e\u56fd", "coord": [-97.0, 38.0]}, {"name": "\u9999\u6e2f\u7279\u522b\u884c\u653f\u533a", "coord": [114.1667, 22.25]}, {"name": "\u610f\u5927\u5229", "coord": [12.8333, 42.8333]}, {"name": "\u8377\u5170", "coord": [5.75, 52.5]}, {"name": "\u53f0\u6e7e\u7701", "coord": [121.0, 23.5]}, {"name": "\u97e9\u56fd", "coord": [127.5, 37.0]}, {"name": "\u9a6c\u6765\u897f\u4e9a", "coord": [112.5, 2.5]}, {"name": "\u4e2d\u56fd", "coord": [105.0, 35.0]}, {"name": "\u5fb7\u56fd", "coord": [9.0, 51.0]}, {"name": "\u745e\u58eb", "coord": [8.0, 47.0]}, {"name": "\u58a8\u897f\u54e5", "coord": [-102.0, 23.0]}, {"name": "\u82f1\u56fd", "coord": [-2.0, 54.0]}, {"name": "\u897f\u73ed\u7259", "coord": [-4.0, 40.0]}, {"name": "\u6cd5\u56fd", "coord": [2.0, 46.0]}, {"name": "\u5357\u975e", "coord": [24.0, -29.0]}, {"name": "\u52a0\u62ff\u5927", "coord": [-95.0, 60.0]}, {"name": "\u6fb3\u5927\u5229\u4e9a", "coord": [133.0, -27.0]}, {"name": "\u963f\u62c9\u4f2f\u8054\u5408\u914b\u957f\u56fd", "coord": [54.0, 24.0]}, {"name": "\u65af\u91cc\u5170\u5361", "coord": [81.0, 7.0]}], "purpose_info": [["\u5546\u4e1a", 684], ["\u4e2a\u4eba", 65], ["\u52a8\u7269\u56ed", 40], ["\u79d1\u7814", 37], ["\u5708\u517b\u7e41\u6b96\u6216\u4eba\u5de5\u7e41\u6b96", 8], ["\u9a6c\u620f\u548c\u5de1\u56de\u5c55\u89c8", 6], ["\u672a\u77e5", 0]]}]