{"1": {"name": "US", "num": 11546, "import_src": ["ID", "CA", "CO", "TH", "IT", "PE", "AU", "DE", "FR", "BR", "MX", "GB", "ZA", "CN", "MG", "MY", "CH", "JP", "HK", "IN"]}, "2": {"name": "JP", "num": 5651, "import_src": ["TH", "MY", "ID", "US", "IT", "BE", "DE", "TW", "EC", "FR", "PH", "NL", "CN", "BR", "KR", "MG", "CZ", "GB", "PE", "SG"]}, "3": {"name": "CH", "num": 5645, "import_src": ["DE", "NL", "FR", "IT", "CO", "TH", "ID", "BE", "US", "DK", "TW", "AT", "GB", "IN", "ES", "AE", "CN", "CA", "HK", "ZA"]}, "4": {"name": "DE", "num": 5192, "import_src": ["EC", "CO", "CH", "US", "BR", "PE", "TH", "PH", "TW", "ID", "ZA", "AU", "IN", "MY", "CN", "MG", "CA", "PA", "JP", "CI"]}, "5": {"name": "FR", "num": 2986, "import_src": ["TH", "EC", "CH", "US", "ID", "CA", "FR", "MG", "JP", "SG", "AU", "TW", "MX", "CN", "FJ", "KR", "AE", "MC", "HK", "MY"]}, "6": {"name": "HK", "num": 2767, "import_src": ["NL", "IT", "FR", "TH", "ID", "CH", "SG", "US", "LA", "JP", "AU", "BE", "BR", "ES", "GB", "DE", "MY", "MG", "CZ", "KR"]}, "7": {"name": "KR", "num": 2637, "import_src": ["ID", "NL", "TW", "IT", "ES", "US", "CN", "JP", "FR", "AU", "DE", "HK", "SG", "TH", "CH", "FJ", "PH", "VN", "GB", "CA"]}, "8": {"name": "SG", "num": 2376, "import_src": ["TH", "IT", "MY", "FR", "ID", "PE", "PH", "NL", "CH", "HK", "US", "AU", "JP", "PA", "BR", "CN", "DE", "ES", "BE", "GB"]}, "9": {"name": "CN", "num": 2319, "import_src": ["IT", "ID", "FR", "DE", "US", "CA", "TH", "GB", "ZA", "CH", "SG", "KR", "DK", "JP", "ES", "CZ", "NL", "GY", "AU", "VN"]}, "10": {"name": "CA", "num": 1781, "import_src": ["US", "TH", "ID", "IT", "FR", "PE", "NL", "CH", "DE", "GB", "CN", "ZW", "HK", "MY", "JP", "ZA", "ES", "BE", "AT", "CM"]}, "11": {"name": "AE", "num": 1667, "import_src": ["NL", "IT", "FR", "ID", "CH", "DE", "BE", "ES", "GB", "US", "CZ", "TH", "AT", "CN", "SG", "QA", "KW", "CA", "OM", "HK"]}, "12": {"name": "TH", "num": 1646, "import_src": ["EC", "NL", "PH", "US", "IT", "CN", "FR", "SG", "ZA", "TW", "ES", "ID", "JP", "CH", "GY", "HK", "MG", "BE", "CZ", "MY"]}, "13": {"name": "IT", "num": 1485, "import_src": ["US", "CH", "ID", "CN", "CO", "JP", "HK", "SG", "TH", "AU", "KR", "CA", "MY", "MX", "AE", "MC", "ZW", "TR", "BR", "AR"]}, "14": {"name": "TW", "num": 1455, "import_src": ["ID", "TH", "BE", "PH", "IT", "FR", "SG", "US", "JP", "NL", "MY", "PE", "BR", "DE", "ES", "CH", "KR", "CA", "GB", "GY"]}, "15": {"name": "GB", "num": 1403, "import_src": ["US", "ID", "AE", "AU", "CA", "CH", "MG", "JE", "SG", "FJ", "LK", "ZA", "CN", "JP", "TH", "IN", "MY", "HK", "TR", "QA"]}, "16": {"name": "RU", "num": 1317, "import_src": ["IT", "TH", "ID", "FR", "BR", "CH", "CZ", "DE", "US", "CN", "CA", "ZW", "AM", "MY", "MC", "ES", "GR", "TR", "UA", "SG"]}, "17": {"name": "MX", "num": 1173, "import_src": ["US", "ES", "IT", "AU", "ID", "FR", "ZW", "CA", "CH", "ZA", "DE", "TH", "GB", "CO", "CU", "NL", "PE", "BR", "AR", "BO"]}, "18": {"name": "TR", "num": 1054, "import_src": ["NL", "ID", "FR", "IT", "CH", "DE", "ES", "TH", "CZ", "GB", "US", "GY", "MG", "AT", "AE", "ML", "CA", "SG", "UZ", "BR"]}, "19": {"name": "NO", "num": 1020, "import_src": ["NL", "ID", "DK", "SE", "CA", "IT", "DE", "CH", "US", "FR", "ZA", "TH", "ES", "ZW", "GB", "BE", "TR", "JP", "AT", "EE"]}, "20": {"name": "BR", "num": 948, "import_src": ["ID", "US", "IT", "FR", "AU", "FJ", "PT", "CH", "DE", "TO", "AE", "GB", "TH", "BE", "ZA", "AR", "EC", "ES", "CA", "NL"]}}